gpu_estimator/__init__.py
gpu_estimator/cli.py
gpu_estimator/estimator.py
gpu_estimator/huggingface_models.py
gpu_estimator/utils.py
gpu_estimator-0.2.0.dist-info/licenses/LICENSE
gpu_estimator-0.2.0.dist-info/METADATA
gpu_estimator-0.2.0.dist-info/WHEEL
gpu_estimator-0.2.0.dist-info/entry_points.txt
gpu_estimator-0.2.0.dist-info/top_level.txt
gpu_estimator-0.2.0.dist-info/RECORD
