Metadata-Version: 2.4
Name: gpu-estimator
Version: 0.2.0
Summary: A Python package for estimating GPU memory requirements and the number of GPUs needed for training machine learning models
Author-email: Hemanth HM <hemanth.hm@gmail.com>
License: MIT
Project-URL: Homepage, https://github.com/hemanth/gpu-estimator
Project-URL: Repository, https://github.com/hemanth/gpu-estimator
Project-URL: Issues, https://github.com/hemanth/gpu-estimator/issues
Project-URL: Documentation, https://github.com/hemanth/gpu-estimator#readme
Keywords: gpu,machine-learning,deep-learning,memory,estimation,huggingface,pytorch
Classifier: Development Status :: 3 - Alpha
Classifier: Intended Audience :: Developers
Classifier: Intended Audience :: Science/Research
Classifier: License :: OSI Approved :: MIT License
Classifier: Programming Language :: Python :: 3
Classifier: Programming Language :: Python :: 3.8
Classifier: Programming Language :: Python :: 3.9
Classifier: Programming Language :: Python :: 3.10
Classifier: Programming Language :: Python :: 3.11
Classifier: Programming Language :: Python :: 3.12
Classifier: Topic :: Scientific/Engineering :: Artificial Intelligence
Classifier: Topic :: System :: Hardware
Requires-Python: >=3.8
License-File: LICENSE
Requires-Dist: numpy>=1.20.0
Requires-Dist: click>=8.0.0
Requires-Dist: transformers>=4.30.0
Requires-Dist: huggingface_hub>=0.16.0
Requires-Dist: torch>=2.0.0
Provides-Extra: dev
Requires-Dist: pytest>=7.0.0; extra == "dev"
Requires-Dist: pytest-cov>=4.0.0; extra == "dev"
Requires-Dist: black>=22.0.0; extra == "dev"
Requires-Dist: flake8>=5.0.0; extra == "dev"
Dynamic: license-file
